signal_groups/__init__.py
signal_groups/api.cpython-35m-x86_64-linux-gnu.so
signal_groups/api.cpython-36m-x86_64-linux-gnu.so
signal_groups/api.cpython-37m-darwin.so
signal_groups/api.cpython-37m-x86_64-linux-gnu.so
signal_groups/api.cpython-38-x86_64-linux-gnu.so
signal_groups/api.cpython-39-x86_64-linux-gnu.so
signal_groups/crypto.cpython-35m-x86_64-linux-gnu.so
signal_groups/crypto.cpython-36m-x86_64-linux-gnu.so
signal_groups/crypto.cpython-37m-darwin.so
signal_groups/crypto.cpython-37m-x86_64-linux-gnu.so
signal_groups/crypto.cpython-38-x86_64-linux-gnu.so
signal_groups/crypto.cpython-39-x86_64-linux-gnu.so
signal_groups/signal_groups.cpython-35m-x86_64-linux-gnu.so
signal_groups/signal_groups.cpython-36m-x86_64-linux-gnu.so
signal_groups/signal_groups.cpython-37m-darwin.so
signal_groups/signal_groups.cpython-37m-x86_64-linux-gnu.so
signal_groups/signal_groups.cpython-38-x86_64-linux-gnu.so
signal_groups/signal_groups.cpython-39-x86_64-linux-gnu.so
signal_groups-0.1.0.dist-info/LICENSE
signal_groups-0.1.0.dist-info/METADATA
signal_groups-0.1.0.dist-info/WHEEL
signal_groups-0.1.0.dist-info/top_level.txt
signal_groups-0.1.0.dist-info/RECORD
