Metadata-Version: 2.1
Name: signal-groups
Version: 0.1.0
Summary: Rust extension providing Python bindings to the v2 signal groups
Home-page: UNKNOWN
License: UNKNOWN
Platform: UNKNOWN
Classifier: License :: OSI Approved :: GNU Affero General Public License v3 or later (AGPLv3+)
Classifier: Development Status :: 3 - Alpha
Classifier: Intended Audience :: Developers
Classifier: Programming Language :: Python
Classifier: Programming Language :: Rust
